{
  "entity_name": "voice_hal_setTelUriFeatureCode",
  "component": "hal",
  "content_hash": "06f2e11403e96d739b17e8ed59d5bcac",
  "response": "**Main purpose and functionality**\n\nThe `voice_hal_setTelUriFeatureCode` function in the `hal` component of the RDK Voice software is used to enable or disable the emergency SIP URI user parameter for a specific voice service and profile. This parameter is used to specify the emergency phone number that should be dialed when the user presses the emergency button on their phone.\n\n**Key operations and data flow**\n\nThe function takes the following input parameters:\n\n* `service`: The voice service affected.\n* `profile`: The voice profile affected.\n* `enable`: A boolean value indicating whether the emergency SIP URI user parameter should be enabled or disabled.\n\nThe function first checks if the input parameters are valid. If they are not, the function returns an error code. Otherwise, the function sets the emergency SIP URI user parameter to the specified value.\n\n**Interaction with other components (if any)**\n\nThe `voice_hal_setTelUriFeatureCode` function interacts with the following components:\n\n* The Voice Service Manager (VSM): The VSM is responsible for managing voice services and profiles. The `voice_hal_setTelUriFeatureCode` function uses the VSM to set the emergency SIP URI user parameter for a specific voice service and profile.\n\n**Important parameters and return values**\n\nThe following are the important parameters and return values of the `voice_hal_setTelUriFeatureCode` function:\n\n* **Parameters:**\n    * `service`: The voice service affected.\n    * `profile`: The voice profile affected.\n    * `enable`: A boolean value indicating whether the emergency SIP URI user parameter should be enabled or disabled.\n* **Return values:**\n    * `RDK_SUCCESS`: The function was successful.\n    * `RDK_FAILURE`: The function failed.\n\n**Any specific RDK-related operations**\n\nThe `voice_hal_setTelUriFeatureCode` function is a specific RDK-related operation. It is used to set the emergency SIP URI user parameter for a specific voice service and profile.",
  "processed_at": "2024-11-14T11:59:38.146517"
}