{
  "entity_name": "qm_conn_close",
  "component": "CcspWifiAgent",
  "content_hash": "1b98af5e1899d733f2fea9dee4ab8ee3",
  "response": "**Analysis of qm_conn_close Function**\n\n**Main Purpose and Functionality**\n* Closes a previously established connection represented by the qm_conn_t object, qc.\n* It deallocates resources associated with the connection and sets its initialization status to false.\n\n**Key Operations and Data Flow**\n* Zeroes out the `qc->res` structure.\n* Checks if the connection is initialized; returns false if not.\n* Closes the file descriptor `qc->fd` if it's valid, and sets it to -1.\n* Sets the `qc->init` flag to false, indicating that the connection is closed.\n\n**Interaction with Other Components**\n* None mentioned in the provided code snippet.\n\n**Important Parameters and Return Values**\n* **Parameters:**\n    * `qm_conn_t *qc`: Pointer to the connection object to be closed.\n* **Return Value:**\n    * `bool`: True if the connection was successfully closed, false otherwise.\n\n**RDK-Related Operations**\n* None specifically mentioned in the code snippet, as it appears to be a generic connection-closing function.\n\n**Additional Notes:**\n* The `MEMZERO` macro is likely used to initialize the `qc->res` structure to all zeroes.\n* The `qc->fd` file descriptor is used for communication with the external entity (not mentioned in the code).",
  "processed_at": "2024-11-13T16:31:10.622206"
}