{
  "entity_name": "pjs_int_t_from_json",
  "component": "CcspWifiAgent",
  "content_hash": "2eda282aeb6a3480dddf351ba77d4766",
  "response": "**1. Main purpose and functionality**\n\nThe `pjs_int_t_from_json` function is responsible for converting a JSON object into an integer value. It is used by the CcspWifiAgent component to parse JSON data received from the network.\n\n**2. Key operations and data flow**\n\nThe function takes three parameters:\n\n* `data`: A pointer to the memory location where the integer value will be stored.\n* `idx`: The index of the integer value in the array.\n* `jsdata`: A pointer to the JSON object to be parsed.\n\nThe function first checks if the `jsdata` parameter is `NULL`. If it is, the function initializes the integer value to 0 and returns `true`. Otherwise, the function checks if the `jsdata` parameter is an integer. If it is not, the function returns `false`. Finally, the function converts the `jsdata` parameter to an integer and stores it in the memory location pointed to by the `data` parameter.\n\n**3. Interaction with other components (if any)**\n\nThe `pjs_int_t_from_json` function does not interact with any other components.\n\n**4. Important parameters and return values**\n\nThe following parameters are important:\n\n* `data`: A pointer to the memory location where the integer value will be stored.\n* `idx`: The index of the integer value in the array.\n* `jsdata`: A pointer to the JSON object to be parsed.\n\nThe following return value is important:\n\n* `true` if the function successfully converted the JSON object to an integer.\n* `false` if the function failed to convert the JSON object to an integer.\n\n**5. Any specific RDK-related operations**\n\nThe `pjs_int_t_from_json` function does not perform any RDK-specific operations.",
  "processed_at": "2024-11-13T16:28:34.551648"
}