{
  "entity_name": "csiMacListHandler",
  "component": "CcspWifiAgent",
  "content_hash": "4622dcffa4c28dd182c81f646c4ba7ce",
  "response": "**1. Main purpose and functionality**\n\nThe csiMacListHandler function responds to RDK CSI events and logs the MAC list changes for the specified CSI session.\n\n**2. Key operations and data flow**\n\na. The function is invoked when a RDK CSI ClientMaclist event is received.\nb. It extracts the CSI session number from the event name.\nc. It retrieves the value of the \"value\" key from the event data.\nd. It logs the updated MAC list for the specified CSI session.\n\n**3. Interaction with other components (if any)**\n\n- This function does not interact with other components directly.\n- It mainly consumes CSI-related events and logs relevant information.\n\n**4. Important parameters and return values**\n\n- **handle**: The RDK bus handle, not used in this function.\n- **event**: The RDK event object containing CSI MAC list information.\n- **subscription**: The RDK event subscription object.\n- The function does not return any value.\n\n**5. Any specific RDK-related operations**\n\n- The function relies on RDK bus event handling and RDK logging mechanisms.\n- It specifically targets CSI (Channel State Information) events related to client MAC list changes.",
  "processed_at": "2024-11-13T14:54:08.337067"
}