{
  "entity_name": "qm_conn_open",
  "component": "CcspWifiAgent",
  "content_hash": "6047aada4178d0fc0527c7bc8a66c86e",
  "response": "**1. Main purpose and functionality:**\n\nThe `qm_conn_open` function initializes a quality manager connection by creating a socket and resolving the hostname.\n\n**2. Key operations and data flow:**\n\n- Initializes the `qm_conn_t` structure with default values.\n- Opens a socket using `qm_conn_open_fd`.\n- Resolves the hostname using `res`.\n\n**3. Interaction with other components (if any):**\n\nThis function is typically used by other components that need to establish a connection to the quality manager.\n\n**4. Important parameters and return values:**\n\n- `qc`: Pointer to the `qm_conn_t` structure to be initialized.\n- Return value: `bool` indicating whether the connection was successfully opened.\n\n**5. Any specific RDK-related operations:**\n\nThis function uses RDK-specific functions for opening a socket (`qm_conn_open_fd`) and resolving the hostname (`res`).",
  "processed_at": "2024-11-13T16:30:55.154818"
}