{
  "entity_name": "ovsdb_tran_comment",
  "component": "CcspWifiAgent",
  "content_hash": "6d29acbb1ff5652278768e7a972e085d",
  "response": "**1. Main purpose and functionality**\n\nThe `ovsdb_tran_comment` function is responsible for generating a JSON object that represents a comment operation to be performed on an OVSDB database transaction. The generated comment object includes information about the operation type (insert, update, mutate, or delete) and the specific key-value pairs that are being modified in the database.\n\n**2. Key operations and data flow**\n\nThe function takes the following parameters:\n\n* `js_array`: A JSON array to which the generated comment object will be added.\n* `oper`: The type of OVSDB operation being performed.\n* `where`: A JSON array representing the key-value pairs that are being modified in the database.\n\nThe function first creates a string that represents the comment text. The comment text includes the operation type and the key-value pairs that are being modified. Then, the function creates a JSON object that represents the comment operation. The JSON object includes the following properties:\n\n* `op`: The type of OVSDB operation being performed.\n* `comment`: The comment text.\n\nThe function then adds the JSON object to the `js_array` and returns true if successful.\n\n**3. Interaction with other components (if any)**\n\nThe `ovsdb_tran_comment` function is typically used by other components in the RDK to add comments to OVSDB transactions. For example, the CcspWifiAgent component uses the `ovsdb_tran_comment` function to add comments to transactions that modify the Wi-Fi configuration.\n\n**4. Important parameters and return values**\n\nThe following are the important parameters and return values of the `ovsdb_tran_comment` function:\n\n* `js_array`: A JSON array to which the generated comment object will be added.\n* `oper`: The type of OVSDB operation being performed.\n* `where`: A JSON array representing the key-value pairs that are being modified in the database.\n\nThe function returns true if successful, or false if an error occurs.\n\n**5. Any specific RDK-related operations**\n\nThe `ovsdb_tran_comment` function is specific to the RDK and is used to add comments to OVSDB transactions.",
  "processed_at": "2024-11-13T16:06:40.066442"
}