{
  "entity_name": "SetNVRamULONGConfiguration",
  "component": "CcspWifiAgent",
  "content_hash": "c169398c8cbe9e0b797bf48c283c2341",
  "response": "**1. Main purpose and functionality**\nThe `SetNVRamULONGConfiguration` function is used to set an unsigned long value in the CcspWifiAgent non-volatile RAM (NVRAM) configuration. It sets the NVRAM configuration parameter specified by the `setting` parameter to the specified `value`. \n\n**2. Key operations and data flow**\nThe function takes two parameters: an NVRAM configuration setting name in the form of a string (`setting`) and a 32-bit unsigned long value to be set (`value`). It uses the `sprintf_s` function to convert the value to a string and then uses the `PSM_Set_Record_Value2` function to set the NVRAM configuration setting. The function returns the result of the `PSM_Set_Record_Value2` function call.\n\n**3. Interaction with other components (if any)**\nThe `SetNVRamULONGConfiguration` function interacts with the PSM (Persistent Storage Manager) component to set the NVRAM configuration setting. The PSM component provides an interface to access and manage NVRAM configuration settings.\n\n**4. Important parameters and return values**\n**Parameters**\n* `setting`: NVRAM configuration setting name in the form of a string.\n* `value`: 32-bit unsigned long value to be set.\n\n**Return values**\nThe function returns the result of the `PSM_Set_Record_Value2` function call, which is an `ANSC_STATUS` value. The possible return values are:\n* `CCSP_SUCCESS`: The operation was successful.\n* `CCSP_FAILURE`: The operation failed.\n\n**5. Any specific RDK-related operations**\nThe `SetNVRamULONGConfiguration` function uses the PSM component, which is an RDK-specific component responsible for managing NVRAM configuration settings.",
  "processed_at": "2024-11-13T14:59:31.304663"
}