{
  "entity_name": "log_module_severity_get",
  "component": "CcspWifiAgent",
  "content_hash": "e81d5947ca301f7c0f472c47ddf4ac07",
  "response": "## Analysis: log_module_severity_get\n\n### 1. Main purpose and functionality\nThe `log_module_severity_get` function retrieves the severity level associated with a specified log module.\n\n### 2. Key operations and data flow\n- The function takes a single parameter, `mod`, which is a log module identifier.\n- It checks if the provided `mod` is valid by comparing it against the `LOG_MODULE_ID_LAST` constant.\n- If `mod` is invalid, the function returns `LOG_SEVERITY_DEFAULT`.\n- If `mod` is valid, the function accesses the `log_module_table` array and retrieves the severity level corresponding to the provided `mod`.\n\n### 3. Interaction with other components\nThis function is part of the CcspWifiAgent component and interacts with the `log_module_table` array, which is a data structure that stores the severity levels for various log modules.\n\n### 4. Important parameters and return values\n- Parameter: `mod` (log_module_t) - The log module identifier.\n- Return value: `log_severity_t` - The severity level for the specified log module.\n\n### 5. Any specific RDK-related operations\nThis function is part of the RDK's logging framework and is used to retrieve the severity level associated with a log module.",
  "processed_at": "2024-11-13T15:53:00.543924"
}