{
  "entity_name": "wifi_getBandSteeringBandUtilizationThreshold",
  "component": "hal",
  "content_hash": "f7a1e3637b07473b01c9978f854e0be6",
  "response": "## **Main Purpose and Functionality**\n---\nThe purpose of the wifi_getBandSteeringBandUtilizationThreshold() function is to read the band steering BandUtilizationThreshold parameter. This is a value set by the user that tells the router when to steer clients to the 5GHz or 2.4GHz band based on the utilization of the bands.\n\n## **Key Operations and Data Flow**\n---\n1. The function takes two parameters:\n   - `radioIndex`: The index of the radio to get the threshold for.\n   - `pBuThreshold`: A pointer to an integer where the threshold value will be stored.\n2. The function retrieves the value of the BandUtilizationThreshold parameter for the specified radio from the driver.\n3. The function returns the status of the operation.\n\n## **Interaction with Other Components**\n---\nThe wifi_getBandSteeringBandUtilizationThreshold() function interacts with the Wi-Fi driver to retrieve the value of the BandUtilizationThreshold parameter.\n\n## **Important Parameters and Return Values**\n---\n| Parameter | Data Type | Description |\n|---|---|---|\n| `radioIndex` | INT | The index of the radio to get the threshold for. |\n| `pBuThreshold` | INT | A pointer to an integer where the threshold value will be stored. |\n| Return Value | INT | The status of the operation. |\n\n## **Specific RDK-Related Operations**\n---\nThis function is part of the RDK Wi-Fi HAL API, which is a set of functions that provides a consistent interface for accessing Wi-Fi functionality from different hardware platforms.",
  "processed_at": "2024-11-14T12:46:33.551568"
}